LICENSE
MANIFEST.in
README.rst
setup.py
wagtail_asciinema/__init__.py
wagtail_asciinema/admin.py
wagtail_asciinema/apps.py
wagtail_asciinema/blocks.py
wagtail_asciinema/models.py
wagtail_asciinema/tests.py
wagtail_asciinema/views.py
wagtail_asciinema.egg-info/PKG-INFO
wagtail_asciinema.egg-info/SOURCES.txt
wagtail_asciinema.egg-info/dependency_links.txt
wagtail_asciinema.egg-info/requires.txt
wagtail_asciinema.egg-info/top_level.txt
wagtail_asciinema/migrations/__init__.py
wagtail_asciinema/templates/wagtail_asciinema/blocks/asciinema_block.html