Metadata-Version: 1.1
Name: wagtail-asciinema
Version: 0.0.2
Summary: Implements Wagtail CMS asciinema integration
Home-page: https://github.com/night-crawler/wagtail-asciinema
Author: night-crawler
Author-email: www@force.fm
License: MIT
Platform: UNKNOWN
Classifier: Environment :: Web Environment
Classifier: Intended Audience :: Developers
Classifier: Operating System :: OS Independent
Classifier: Programming Language :: Python
Classifier: Programming Language :: Python :: 3
Classifier: Programming Language :: Python :: 3.5
Classifier: Framework :: Django
Classifier: License :: OSI Approved :: MIT License
